MANIFEST.in
README.md
requirements.txt
setup.cfg
setup.py
rqalpha_data/VERSION.txt
rqalpha_data/__init__.py
rqalpha_data/datasource.py
rqalpha_data/datetime_utils.py
rqalpha_data/demo.py
rqalpha_data/quant_utils.py
rqalpha_data.egg-info/PKG-INFO
rqalpha_data.egg-info/SOURCES.txt
rqalpha_data.egg-info/dependency_links.txt
rqalpha_data.egg-info/requires.txt
rqalpha_data.egg-info/top_level.txt