Metadata-Version: 1.1
Name: rqalpha-data
Version: 0.0.7
Summary: A utility for RQAlpha to directly use data
Home-page: https://github.com/sixquant/rqalpha-data
Author: sixquant
Author-email: public@sixquant.com
License: MIT
Keywords: RiceQuant RQAlpha finance data
Platform: UNKNOWN
Classifier: Development Status :: 3 - Alpha
Classifier: Programming Language :: Python
Classifier: Operating System :: Microsoft :: Windows
Classifier: Operating System :: Unix
Classifier: Programming Language :: Python :: 2.7
Classifier: Programming Language :: Python :: 3.4
Classifier: Programming Language :: Python :: 3.5
Classifier: Programming Language :: Python :: 3.6
Classifier: License :: OSI Approved :: MIT License
